genplanner/__init__.py
genplanner/_config.py
genplanner/_rust.cpython-311-darwin.so
genplanner/genplanner.py
genplanner/tasks/__init__.py
genplanner/tasks/base_splitters.py
genplanner/tasks/block_splitters.py
genplanner/tasks/func_zone_splitters.py
genplanner/tasks/terr_zone_splitters.py
genplanner/utils/__init__.py
genplanner/utils/geom_utils.py
genplanner/zoning/__init__.py
genplanner/zoning/_basic_func_zones.py
genplanner/zoning/_basic_terr_zones.py
genplanner/zoning/func_zones.py
genplanner/zoning/genplan.py
genplanner/zoning/terr_zones.py
genplanner-0.1.1.dist-info/METADATA
genplanner-0.1.1.dist-info/WHEEL
genplanner-0.1.1.dist-info/licenses/LICENSE
genplanner-0.1.1.dist-info/RECORD
