Metadata-Version: 2.4
Name: genplanner
Version: 0.1.1
Requires-Dist: tqdm>=4.66.2,<5.0.0
Requires-Dist: numpy>=2.1.3,<3.0.0
Requires-Dist: pandas>=2.2.0,<3.0.0
Requires-Dist: geopandas>=1.0.0,<2.0.0
Requires-Dist: loguru>=0.7.2,<1.0.0
Requires-Dist: scipy>=1.13.1,<2.0.0
Requires-Dist: pulp>=3.1.1,<4.0.0
License-File: LICENSE
Summary: GenPlanner python+rust library
Author-email: DDonnyy <63115678+DDonnyy@users.noreply.github.com>
Requires-Python: >=3.11, <3.13
